{
	"name": "DF_Chicago",
	"properties": {
		"type": "MappingDataFlow",
		"typeProperties": {
			"sources": [
				{
					"dataset": {
						"referenceName": "Chicago_22_23",
						"type": "DatasetReference"
					},
					"name": "source1"
				}
			],
			"sinks": [],
			"transformations": [
				{
					"name": "derivedColumn1"
				},
				{
					"name": "flatten1"
				},
				{
					"name": "derivedColumn2"
				},
				{
					"name": "derivedColumn3"
				},
				{
					"name": "derivedColumn4"
				},
				{
					"name": "derivedColumn5"
				}
			],
			"scriptLines": [
				"source(output(",
				"          {Inspection ID} as string,",
				"          {DBA Name} as string,",
				"          {AKA Name} as string,",
				"          {License #} as string,",
				"          {Facility Type} as string,",
				"          Risk as string,",
				"          Address as string,",
				"          City as string,",
				"          State as string,",
				"          Zip as string,",
				"          {Inspection Date} as string,",
				"          {Inspection Type} as string,",
				"          Results as string,",
				"          Violations as string,",
				"          Latitude as string,",
				"          Longitude as string,",
				"          Location as string",
				"     ),",
				"     allowSchemaDrift: true,",
				"     validateSchema: false,",
				"     ignoreNoFilesFound: false) ~> source1",
				"source1 derive(Violations = iif(isNull(Violations), 'Unknown', Violations),",
				"          {DBA Name} = iif(isNull({DBA Name}), 'Unknown', {DBA Name}),",
				"          {AKA Name} = iif(isNull({AKA Name}), 'Unknown', {AKA Name}),",
				"          {License #} = iif(isNull({License #}), 'Unknown', {License #}),",
				"          {Facility Type} = iif(isNull({Facility Type}), 'Unknown', {Facility Type}),",
				"          Risk = iif(isNull(Risk), 'Unknown', Risk),",
				"          Address = iif(isNull(Address), 'Unknown', Address),",
				"          City = iif(isNull(City), 'Unknown', City),",
				"          State = iif(isNull(State), 'Unknown', State),",
				"          Zip = iif(isNull(Zip),'0', Zip),",
				"          Latitude = iif(isNull(Latitude), '0.0', Latitude),",
				"          Longitude = iif(isNull(Longitude), '0.0', Longitude),",
				"          Location = iif(isNull(Location), '(0.0, 0.0)', Location)) ~> derivedColumn1",
				"derivedColumn3 foldDown(unroll(Violations),",
				"     mapColumn(",
				"          {Inspection ID},",
				"          {DBA Name},",
				"          {AKA Name},",
				"          {License #},",
				"          {Facility Type},",
				"          Risk,",
				"          Address,",
				"          City,",
				"          State,",
				"          Zip,",
				"          {Inspection Date},",
				"          {Inspection Type},",
				"          Results,",
				"          Violations,",
				"          Latitude,",
				"          Longitude,",
				"          Location",
				"     ),",
				"     skipDuplicateMapInputs: false,",
				"     skipDuplicateMapOutputs: false) ~> flatten1",
				"flatten1 derive(ViolationComments = split(Violations, '- Comments:')[2],",
				"          ViolationID = split(Violations, '.')[1],",
				"          ViolationType = split(Violations, '.')[2]) ~> derivedColumn2",
				"derivedColumn1 derive(Violations = split(Violations,'|')) ~> derivedColumn3",
				"derivedColumn2 derive(ViolationComments = trim(ViolationComments),",
				"          ViolationID = trim(ViolationID),",
				"          ViolationType = trim(ViolationType),",
				"          {Inspection ID} = toInteger({Inspection ID}),",
				"          {License #} = toInteger({License #}),",
				"          Zip = toInteger(Zip),",
				"          Latitude = toFloat(Latitude),",
				"          Longitude = toFloat(Longitude)) ~> derivedColumn4",
				"derivedColumn4 derive(ViolationID = toInteger(ViolationID),",
				"          Inspection_ID = {Inspection ID},",
				"          DBA_Name = {DBA Name},",
				"          AKA_Name = {AKA Name},",
				"          {License_#} = {License #},",
				"          Facility_Type = {Facility Type},",
				"          Inspection_Date = {Inspection Date},",
				"          Inspection_Type = {Inspection Type},",
				"          Violation_Comments = ViolationComments,",
				"          Violation_ID = ViolationID,",
				"          Violation_Type = ViolationType) ~> derivedColumn5"
			]
		}
	}
}